odoo/addons/sale_invoice_cash_rounding_default/LICENSE
odoo/addons/sale_invoice_cash_rounding_default/README.rst
odoo/addons/sale_invoice_cash_rounding_default/__init__.py
odoo/addons/sale_invoice_cash_rounding_default/__manifest__.py
odoo/addons/sale_invoice_cash_rounding_default/images/screen.png
odoo/addons/sale_invoice_cash_rounding_default/models/__init__.py
odoo/addons/sale_invoice_cash_rounding_default/models/res_company.py
odoo/addons/sale_invoice_cash_rounding_default/models/res_config_settings.py
odoo/addons/sale_invoice_cash_rounding_default/models/sale_order.py
odoo/addons/sale_invoice_cash_rounding_default/static/description/icon.png
odoo/addons/sale_invoice_cash_rounding_default/static/description/index.html
odoo/addons/sale_invoice_cash_rounding_default/tests/TEST_INSTRUCTIONS.rst
odoo/addons/sale_invoice_cash_rounding_default/views/res_config_settings_views.xml
odoo/addons/sale_invoice_cash_rounding_default/wizard/__init__.py
odoo/addons/sale_invoice_cash_rounding_default/wizard/sale_advance_payment_inv.py
odoo_addon_sale_invoice_cash_rounding_default-18.0.1.0.0.dist-info/METADATA
odoo_addon_sale_invoice_cash_rounding_default-18.0.1.0.0.dist-info/WHEEL
odoo_addon_sale_invoice_cash_rounding_default-18.0.1.0.0.dist-info/top_level.txt
odoo_addon_sale_invoice_cash_rounding_default-18.0.1.0.0.dist-info/RECORD
