Metadata-Version: 2.1
Name: odoo-addon-sale_invoice_cash_rounding_default
Version: 18.0.1.0.0
Requires-Python: >=3.10
Requires-Dist: odoo==18.0.*
Summary: Apply default cash rounding when invoicing sale orders.
Home-page: https://www.mint-system.ch/
License: AGPL-3
Author: Mint System GmbH
Classifier: Programming Language :: Python
Classifier: Framework :: Odoo
Classifier: Framework :: Odoo :: 18.0
Classifier: License :: OSI Approved :: GNU Affero General Public License v3
